datagouv/__init__.py
datagouv/api_client/__init__.py
datagouv/api_client/_data_requestor.py
datagouv/api_client/_datagouv_client.py
datagouv/api_client/_datasets_service.py
datagouv/downloader/__init__.py
datagouv/downloader/_resources_downloader.py
datagouv/downloader/_resources_downloader__test.py
datagouv/downloader/_utils.py
datagouv/main.py
datagouv_python-0.1.5.dist-info/LICENSE
datagouv_python-0.1.5.dist-info/METADATA
datagouv_python-0.1.5.dist-info/WHEEL
datagouv_python-0.1.5.dist-info/entry_points.txt
datagouv_python-0.1.5.dist-info/RECORD
