Metadata-Version: 2.1
Name: datagouv-python
Version: 0.1.5
Summary: Unofficial python client for `data.gouv.fr`
Home-page: https://github.com/MaximePawlakFr/datagouv-python
License: GPL-3.0-or-later
Keywords: open-data,opendata,government
Author: Maxime Pawlak
Author-email: maxime.pawlak@amatek.fr
Requires-Python: >=3.9,<4.0
Classifier: License :: OSI Approved :: GNU General Public License v3 or later (GPLv3+)
Classifier: Programming Language :: Python :: 3
Classifier: Programming Language :: Python :: 3.9
Classifier: Programming Language :: Python :: 3.10
Classifier: Programming Language :: Python :: 3.11
Classifier: Programming Language :: Python :: 3.12
Requires-Dist: pandas (>=2.0.0,<3.0.0)
Requires-Dist: requests (>=2.31.0,<3.0.0)
Requires-Dist: toml (>=0.10.2,<0.11.0)
Requires-Dist: tqdm (>=4.66.2,<5.0.0)
Project-URL: Repository, https://github.com/MaximePawlakFr/datagouv-python
